pyrustymd-0.1.3.dist-info/METADATA
pyrustymd-0.1.3.dist-info/WHEEL
pyrustymd-0.1.3.dist-info/license_files/LICENSE
pyrustymd/__init__.py
pyrustymd/pyrustymd.cpython-311-powerpc64le-linux-gnu.so
pyrustymd-0.1.3.dist-info/RECORD
